comm/__init__.py
comm/base_comm.py
comm-0.1.0.dist-info/LICENSE
comm-0.1.0.dist-info/METADATA
comm-0.1.0.dist-info/WHEEL
comm-0.1.0.dist-info/top_level.txt
comm-0.1.0.dist-info/RECORD
