Metadata-Version: 2.1
Name: comm
Version: 0.1.0
Summary: Jupyter Python Comm implementation, for usage in ipykernel, xeus-python etc.
Home-page: https://github.com/martinRenou/comm
Author: Jupyter contributors
License: BSD 3-Clause
Keywords: jupyter,ipykernel,xeus-python
Requires-Python: >=3.6
License-File: LICENSE
